AUTHORS.rst
HISTORY.rst
LICENSE.txt
MANIFEST.in
README.rst
setup.py
test_schedule.py
aioschedule/__init__.py
aioschedule/package.json
canonical.egg-info/PKG-INFO
canonical.egg-info/SOURCES.txt
canonical.egg-info/dependency_links.txt
canonical.egg-info/top_level.txt
docs/conf.py